[{"Cobb v. Malone": ["5648729", 27, "https://cite.case.law/ala/92/630/", "1890-11", "Ala."]}, {"James v. State": ["2374090", 21, "https://cite.case.law/tex-crim/63/75/", "1911-05-31", "Tex."]}, {"Mockowik v. Kansas City": ["2193078", 20, "https://cite.case.law/mo/196/550/", "1906-05-30", "Mo."]}, {"Borgnis v. Falk Co.": ["8699375", 20, "https://cite.case.law/wis/147/327/", "1911-11-14", "Wis."]}, {"St. Louis Southwestern Ry. Co. of Texas v. Wadsack": ["8269908", 20, "https://cite.case.law/sw/166/42/", "1914-03-19", "Tex."]}]